[
  {
    "id": 1,
    "name": "Ratón Gris",
    "image": "https://static.wikia.nocookie.net/dofus/images/c/c6/Grey_Mouse.png",
    "level": "1",
    "subzone": "Criptas del cementerio",
    "zone": "Amakna",
    "step": 1,
    "type": "monster"
  },
  {
    "id": 2,
    "name": "Moskito",
    "image": "https://static.wikia.nocookie.net/dofus/images/7/7f/Moskito.png",
    "level": "16 - 20",
    "subzone": "Linde del mosque maléfico, Campo de Amakna",
    "zone": "Amakna",
    "step": 1,
    "type": "monster"
  },
  {
    "id": 3,
    "name": "Arakna",
    "image": "./assets/img/arakna.webp",
    "level": "16 - 20",
    "subzone": "Campo de amakna, Piedemonte de los crujidores, Campo de los Ingals",
    "zone": "Varias",
    "step": 1,
    "type": "monster"
  },
  {
    "id": 4,
    "name": "Jalatín Blanco",
    "image": "./assets/img/jalatin_blanco.webp",
    "level": "22 - 30",
    "subzone": "Rincón de los jalatós, Tainela",
    "zone": "Amakna",
    "step": 1,
    "type": "monster"
  },
  {
    "id": 5,
    "name": "Jalatín Negro",
    "image": "./assets/img/jalatin_negro.webp",
    "level": "22 - 30",
    "subzone": "Rincón de los jalatós, Tainela",
    "zone": "Amakna",
    "step": 1,
    "type": "monster"
  },
  {
    "id": 6,
    "name": "Tofu Maléfico",
    "image": "./assets/img/tofu_malefico.webp",
    "level": "32 - 40",
    "subzone": "Bosque maléfico",
    "zone": "Amakna",
    "step": 1,
    "type": "monster"
  },
  {
    "id": 7,
    "name": "Arakna Enferma",
    "image": "./assets/img/arakna_enferma.webp",
    "level": "11 - 15",
    "subzone": "Subterráneos de Astrub",
    "zone": "Astrub",
    "step": 1,
    "type": "monster"
  },
  {
    "id": 8,
    "name": "Pío Azul",
    "image": "./assets/img/pio_azul.webp",
    "level": "11 - 15",
    "subzone": "Bahía de Sufokia",
    "zone": "Sufokia",
    "step": 1,
    "type": "monster"
  },
  {
    "id": 9,
    "name": "Pío Amarillo",
    "image": "./assets/img/pio_amarillo.webp",
    "level": "11 - 15",
    "subzone": "Bahía de Sufokia",
    "zone": "Sufokia",
    "step": 1,
    "type": "monster"
  },
  {
    "id": 10,
    "name": "Pío Rojo",
    "image": "./assets/img/pio_rojo.webp",
    "level": "11 - 15",
    "subzone": "Fortificación de Bonta",
    "zone": "Bonta",
    "step": 1,
    "type": "monster"
  },
  {
    "id": 11,
    "name": "Pío Verde",
    "image": "./assets/img/pio_verde.webp",
    "level": "11 - 15",
    "subzone": "Bahía de Sufokia",
    "zone": "Sufokia",
    "step": 1,
    "type": "monster"
  },
  {
    "id": 12,
    "name": "Pío Violeta",
    "image": "./assets/img/pio_violeta.webp",
    "level": "11 - 15",
    "subzone": "Bahía de Sufokia",
    "zone": "Sufokia",
    "step": 1,
    "type": "monster"
  },
  {
    "id": 13,
    "name": "Llamita Aire",
    "image": "./assets/img/llamita_aire.webp",
    "level": "34 - 42",
    "subzone": "Llanura de los escarahojas",
    "zone": "Amakna",
    "step": 1,
    "type": "monster"
  },
  {
    "id": 14,
    "name": "Llamita Agua",
    "image": "./assets/img/llamita_agua.webp",
    "level": "34 - 42",
    "subzone": "Llanura de los escarahojas",
    "zone": "Amakna",
    "step": 1,
    "type": "monster"
  },
  {
    "id": 15,
    "name": "Llamita Fuego",
    "image": "./assets/img/llamita_fuego.webp",
    "level": "34 - 42",
    "subzone": "Llanura de los escarahojas",
    "zone": "Amakna",
    "step": 1,
    "type": "monster"
  },
  {
    "id": 16,
    "name": "Llamita Tierra",
    "image": "./assets/img/llamita_tierra.webp",
    "level": "34 - 42",
    "subzone": "Llanura de los escarahojas",
    "zone": "Amakna",
    "step": 1,
    "type": "monster"
  },
  {
    "id": 17,
    "name": "Cangrejo",
    "image": "./assets/img/cangrejo.webp",
    "level": "42 - 50",
    "subzone": "Ribera del golfo sufokeño",
    "zone": "Sufokia",
    "step": 1,
    "type": "monster"
  },
  {
    "id": 18,
    "name": "Larva Azul",
    "image": "./assets/img/larva_azul.webp",
    "level": "16 - 20",
    "subzone": "Linde del bosque maléfico, Praderas de Astrub",
    "zone": "Varias",
    "step": 1,
    "type": "monster"
  },
  {
    "id": 19,
    "name": "Pío Rosa",
    "image": "./assets/img/pio_rosa.webp",
    "level": "11 - 15",
    "subzone": "Bahía de Sufokia",
    "zone": "Sufokia",
    "step": 1,
    "type": "monster"
  },
  {
    "id": 20,
    "name": "Tofu",
    "image": "./assets/img/tofu.webp",
    "level": "32 - 40",
    "subzone": "Campo de los ingals",
    "zone": "Amakna",
    "step": 1,
    "type": "monster"
  },
  {
    "id": 21,
    "name": "Tofu Enfermo",
    "image": "./assets/img/tofu_enfermo.webp",
    "level": "11 - 15",
    "subzone": "Subterráneos de Astrub",
    "zone": "Astrub",
    "step": 2,
    "type": "monster"
  },
  {
    "id": 22,
    "name": "Champi Champ",
    "image": "./assets/img/champi_champ.webp",
    "level": "16 - 20",
    "subzone": "Rincón de los jalatós",
    "zone": "Amakna",
    "step": 2,
    "type": "monster"
  },
  {
    "id": 23,
    "name": "Diente de León Diabólico",
    "image": "./assets/img/diente_de_leon_diabolico.webp",
    "level": "16 - 20",
    "subzone": "Campos de Astrub",
    "zone": "Astrub",
    "step": 2,
    "type": "monster"
  },
  {
    "id": 24,
    "name": "Arakna de Alcantarilla",
    "image": "./assets/img/arakna_de_alcantarilla.webp",
    "level": "22 - 30",
    "subzone": "Alcantarillas de Astrub",
    "zone": "Astrub",
    "step": 2,
    "type": "monster"
  },
  {
    "id": 25,
    "name": "Bandido Manco",
    "image": "./assets/img/bandido_manco.webp",
    "level": "42 - 50",
    "subzone": "Pasaje hacia Brakmar",
    "zone": "Amakna",
    "step": 2,
    "type": "monster"
  },
  {
    "id": 26,
    "name": "Rosa Demoniaca",
    "image": "./assets/img/rosa_demoniaca.webp",
    "level": "16 - 20",
    "subzone": "Campos de Astrub",
    "zone": "Astrub",
    "step": 2,
    "type": "monster"
  },
  {
    "id": 27,
    "name": "Gelatina Azul",
    "image": "./assets/img/gelatina_azul.webp",
    "level": "46 - 62",
    "subzone": "Península de las gelatinas",
    "zone": "Amakna",
    "step": 2,
    "type": "monster"
  },
  {
    "id": 28,
    "name": "Kwoan",
    "image": "./assets/img/kwoan.webp",
    "level": "32 - 40",
    "subzone": "Cementerio de Amakna",
    "zone": "Amakna",
    "step": 2,
    "type": "monster"
  },
  {
    "id": 29,
    "name": "Larva Verde",
    "image": "./assets/img/larva_verde.webp",
    "level": "16 - 20",
    "subzone": "Praderas de Astrub",
    "zone": "Astrub",
    "step": 2,
    "type": "monster"
  },
  {
    "id": 30,
    "name": "Jalató",
    "image": "./assets/img/jalato.webp",
    "level": "22 - 30",
    "subzone": "Rincón de los jalatós",
    "zone": "Amakna",
    "step": 2,
    "type": "monster"
  },
  {
    "id": 31,
    "name": "Kólerat",
    "image": "./assets/img/kolerat.webp",
    "level": "62 - 70",
    "subzone": "Rincón de los jalatós",
    "zone": "Amakna",
    "step": 2,
    "type": "monster"
  },
  {
    "id": 32,
    "name": "Gelatina de menta",
    "image": "./assets/img/gelatina_de_menta.webp",
    "level": "50 - 62",
    "subzone": "Península de las gelatinas",
    "zone": "Amakna",
    "step": 2,
    "type": "monster"
  },
  {
    "id": 33,
    "name": "Larva naranja",
    "image": "./assets/img/larva_naranja.webp",
    "level": "16 - 20",
    "subzone": "Praderas de Astrub",
    "zone": "Astrub",
    "step": 2,
    "type": "monster"
  },
  {
    "id": 34,
    "name": "Panadero oscuro",
    "image": "./assets/img/panadero_oscuro.webp",
    "level": "35 - 47",
    "subzone": "Territorio de los bandidos",
    "zone": "Amakna",
    "step": 2,
    "type": "monster"
  },
  {
    "id": 35,
    "name": "Black pekewabbit",
    "image": "./assets/img/black_pekewabbit.webp",
    "level": "46 - 54",
    "subzone": "Isla zanahowia",
    "zone": "Archipiélago Wabbit",
    "step": 2,
    "type": "monster"
  },
  {
    "id": 36,
    "name": "Pekewabbit",
    "image": "./assets/img/pekewabbit.webp",
    "level": "41 - 49",
    "subzone": "Isla zanahowia",
    "zone": "Archipiélago Wabbit",
    "step": 2,
    "type": "monster"
  },
  {
    "id": 300,
    "name": "Blop Coco Real",
    "image": "./assets/img/blop_coco_real.webp",
    "level": "60",
    "subzone": "Lago de Cania",
    "zone": "Llanuras de Cania",
    "step": 17,
    "type": "boss"
  },
  {
    "id": 301,
    "name": "Blop Guinda Real",
    "image": "./assets/img/blop_guinda_real.webp",
    "level": "60",
    "subzone": "Lago de Cania",
    "zone": "Llanuras de Cania",
    "step": 17,
    "type": "boss"
  },
  {
    "id": 302,
    "name": "Blop Índigo Real",
    "image": "./assets/img/blop_indigo_real.webp",
    "level": "60",
    "subzone": "Lago de Cania",
    "zone": "Llanuras de Cania",
    "step": 17,
    "type": "boss"
  },
  {
    "id": 303,
    "name": "Blop Reineta Real",
    "image": "./assets/img/blop_reineta_real.webp",
    "level": "60",
    "subzone": "Lago de Cania",
    "zone": "Llanuras de Cania",
    "step": 17,
    "type": "boss"
  },
  {
    "id": 304,
    "name": "Bworka",
    "image": "./assets/img/bworka.webp",
    "level": "50",
    "subzone": "Pueblo de los Bworks",
    "zone": "Amakna",
    "step": 17,
    "type": "boss"
  },
  {
    "id": 305,
    "name": "Deminobola",
    "image": "./assets/img/deminobola.webp",
    "level": "108 - 120",
    "subzone": "Isla del Minotauroro",
    "zone": "Isla del Minotauroro",
    "step": 17,
    "type": "boss"
  },
  {
    "id": 306,
    "name": "Dragocerdo",
    "image": "./assets/img/dragocerdo.webp",
    "level": "100",
    "subzone": "Territorio de los porcos",
    "zone": "Amakna",
    "step": 17,
    "type": "boss"
  },
  {
    "id": 307,
    "name": "Escarajefe Dorado",
    "image": "./assets/img/escarajefe_dorado.webp",
    "level": "40",
    "subzone": "Llanura de los escarahojas",
    "zone": "Amakna",
    "step": 17,
    "type": "boss"
  },
  {
    "id": 308,
    "name": "Gelatina Real Azul",
    "image": "./assets/img/gelatina_real_azul.webp",
    "level": "60",
    "subzone": "Gelaxta Dimensión",
    "zone": "Amakna",
    "step": 17,
    "type": "boss"
  },
  {
    "id": 309,
    "name": "Gelatina Real de Menta",
    "image": "./assets/img/gelatina_real_de_menta.webp",
    "level": "60",
    "subzone": "Gelaxta Dimensión",
    "zone": "Amakna",
    "step": 17,
    "type": "boss"
  },
  {
    "id": 310,
    "name": "Girasol Hambriento",
    "image": "./assets/img/girasol_hambriento.webp",
    "level": "20",
    "subzone": "Campos de Astrub",
    "zone": "Astrub",
    "step": 17,
    "type": "boss"
  },
  {
    "id": 311,
    "name": "Jalató Real",
    "image": "./assets/img/jalato_real.webp",
    "level": "30",
    "subzone": "Tainela",
    "zone": "Astrub",
    "step": 17,
    "type": "boss"
  },
  {
    "id": 312,
    "name": "Minotauroro",
    "image": "./assets/img/minotauroro.webp",
    "level": "120",
    "subzone": "Isla del Minotauroro",
    "zone": "Isla del Minotauroro",
    "step": 17,
    "type": "boss"
  },
  {
    "id": 313,
    "name": "Mob Lasponja",
    "image": "./assets/img/mob_lasponja.webp",
    "level": "20",
    "subzone": "Calas de Astrub",
    "zone": "Astrub",
    "step": 17,
    "type": "boss"
  },
  {
    "id": 314,
    "name": "Mominotauro",
    "image": "./assets/img/mominotauro.webp",
    "level": "108 - 120",
    "subzone": "Isla del Minotauroro",
    "zone": "Isla del Minotauroro",
    "step": 17,
    "type": "boss"
  },
  {
    "id": 315,
    "name": "Rata Blanca",
    "image": "./assets/img/rata_blanca.webp",
    "level": "110 - 150",
    "subzone": "Promontorio de los cielos",
    "zone": "Bonta",
    "step": 17,
    "type": "boss"
  },
  {
    "id": 316,
    "name": "Rata Negra",
    "image": "./assets/img/rata_negra.webp",
    "level": "110 - 150",
    "subzone": "Yunque",
    "zone": "Brakmar",
    "step": 17,
    "type": "boss"
  },
  {
    "id": 317,
    "name": "Shin Larva",
    "image": "./assets/img/shin_larva.webp",
    "level": "50",
    "subzone": "La montaña de los crujidores",
    "zone": "Amakna",
    "step": 17,
    "type": "boss"
  },
  {
    "id": 318,
    "name": "Tofu Real",
    "image": "./assets/img/tofu_real.webp",
    "level": "120",
    "subzone": "Campos de Ingals",
    "zone": "Amakna",
    "step": 17,
    "type": "boss"
  },
  {
    "id": 319,
    "name": "Wabbit GM",
    "image": "./assets/img/Wabbit_gm.webp",
    "level": "110 - 150",
    "subzone": "Subterráneos de los Wabbits",
    "zone": "Archipiélago Wabbit",
    "step": 17,
    "type": "boss"
  },
  {
    "id": 320,
    "name": "Abráknido Ancestral",
    "image": "./assets/img/abraknido_ancestral.webp",
    "level": "90",
    "subzone": "Bosque Oscuro",
    "zone": "Bosque de los Abráknidos",
    "step": 17,
    "type": "boss"
  },
  {
    "id": 321,
    "name": "Blop Multicolor Real",
    "image": "./assets/img/blop_multicolor_real.webp",
    "level": "120",
    "subzone": "Lago de Cania",
    "zone": "Llanuras de Cania",
    "step": 17,
    "type": "boss"
  },
  {
    "id": 322,
    "name": "Coralador Magistral",
    "image": "./assets/img/coralador_magistral.webp",
    "level": "50",
    "subzone": "Playa Coral",
    "zone": "Isla de Otomai",
    "step": 17,
    "type": "boss"
  },
  {
    "id": 323,
    "name": "Crujidor Legendario",
    "image": "./assets/img/crujidor_legendario.webp",
    "level": "70",
    "subzone": "La montaña de los crujidores",
    "zone": "Amakna",
    "step": 17,
    "type": "boss"
  },
  {
    "id": 324,
    "name": "Gelatina Real de Fresa",
    "image": "./assets/img/gelatina_real_de_fresa.webp",
    "level": "60",
    "subzone": "Gelaxta Dimensión",
    "zone": "Amakna",
    "step": 17,
    "type": "boss"
  },
  {
    "id": 325,
    "name": "Guardiana de alcantarilla",
    "image": "./assets/img/guardiana_de_alcantarilla.webp",
    "level": "145 - 165",
    "subzone": "Alcantarillas",
    "zone": "Varios",
    "step": 17,
    "type": "boss"
  },
  {
    "id": 326,
    "name": "Gurlo el Terrible",
    "image": "./assets/img/gurlo_el_terrible.webp",
    "level": "70",
    "subzone": "Tubera sin Fondo",
    "zone": "Isla de Otomai",
    "step": 17,
    "type": "boss"
  },
  {
    "id": 327,
    "name": "Hanshi",
    "image": "./assets/img/hanshi.webp",
    "level": "140",
    "subzone": "Airelada",
    "zone": "Pandala",
    "step": 17,
    "type": "boss"
  },
  {
    "id": 328,
    "name": "Hell Mina",
    "image": "./assets/img/hell_mina.webp",
    "level": "140",
    "subzone": "Bosque maléfico",
    "zone": "Amakna",
    "step": 17,
    "type": "boss"
  },
  {
    "id": 329,
    "name": "Maestro Cuerbok",
    "image": "./assets/img/maestro_cuerbok.webp",
    "level": "110 - 220",
    "subzone": "Morada de Cuerbok",
    "zone": "Llanuras de Cania",
    "step": 17,
    "type": "boss"
  },
  {
    "id": 330,
    "name": "Maxilubo",
    "image": "./assets/img/maxilubo.webp",
    "level": "100",
    "subzone": "Altos de los Aullidos",
    "zone": "Landas de Sidimote",
    "step": 17,
    "type": "boss"
  },
  {
    "id": 331,
    "name": "Moon",
    "image": "./assets/img/moon.webp",
    "level": "100",
    "subzone": "Jungla Prohibida",
    "zone": "Isla de Moon",
    "step": 17,
    "type": "boss"
  },
  {
    "id": 332,
    "name": "Moon",
    "image": "./assets/img/moon.webp",
    "level": "100",
    "subzone": "Jungla Prohibida",
    "zone": "Isla de Moon",
    "step": 17,
    "type": "boss"
  },
  {
    "id": 333,
    "name": "Tanukui San",
    "image": "./assets/img/tanukui_San.webp",
    "level": "130",
    "subzone": "Tierralada",
    "zone": "Pandala",
    "step": 17,
    "type": "boss"
  },{
    "id": 334,
    "name": "Trankitronko",
    "image": "./assets/img/trankitronko.webp",
    "level": "100",
    "subzone": "Cañon Savaje",
    "zone": "Montaña de los Koalaks",
    "step": 17,
    "type": "boss"
  },
  {
    "id": 335,
    "name": "Tynril Absorto",
    "image": "./assets/img/tynril_absorto.webp",
    "level": "140 - 280",
    "subzone": "Jungla Oscura",
    "zone": "Isla de Otomai",
    "step": 17,
    "type": "boss"
  },
  {
    "id": 336,
    "name": "Tynril Atónito",
    "image": "./assets/img/tynril_atónito.webp",
    "level": "140 - 280",
    "subzone": "Jungla Oscura",
    "zone": "Isla de Otomai",
    "step": 17,
    "type": "boss"
  },
  {
    "id": 337,
    "name": "Tynril Estupefacto",
    "image": "./assets/img/tynril_estupefacto.webp",
    "level": "140 - 280",
    "subzone": "Jungla Oscura",
    "zone": "Isla de Otomai",
    "step": 17,
    "type": "boss"
  },
  {
    "id": 338,
    "name": "Tynril Pérfido",
    "image": "./assets/img/tynril_perfido.webp",
    "level": "140 - 280",
    "subzone": "Jungla Oscura",
    "zone": "Isla de Otomai",
    "step": 17,
    "type": "boss"
  },
  {
    "id": 339,
    "name": "Wey Wabbit",
    "image": "./assets/img/wey_wabbit.webp",
    "level": "60",
    "subzone": "Islote la Cowona",
    "zone": "Archipiélago Wabbit",
    "step": 17,
    "type": "boss"
  },
  {
    "id": 340,
    "name": "Bworker",
    "image": "./assets/img/bworker.webp",
    "level": "180",
    "subzone": "Gisgul",
    "zone": "Landas de Sidimote",
    "step": 17,
    "type": "boss"
  },
  {
    "id": 341,
    "name": "Cocabulia",
    "image": "./assets/img/cocabulia.webp",
    "level": "120",
    "subzone": "Península de los Dragohuevos",
    "zone": "Amakna",
    "step": 17,
    "type": "boss"
  },
  {
    "id": 342,
    "name": "Funámbola",
    "image": "./assets/img/funámbola.webp",
    "level": "130 - 140",
    "subzone": "Fuegodala",
    "zone": "Pandala",
    "step": 17,
    "type": "boss"
  },
  {
    "id": 343,
    "name": "Gelatina Real de Limón",
    "image": "./assets/img/gelatina_real_de_limon.webp",
    "level": "60",
    "subzone": "Gelaxta Dimensión",
    "zone": "Amakna",
    "step": 17,
    "type": "boss"
  },
  {
    "id": 344,
    "name": "Kimbo",
    "image": "./assets/img/kimbo.webp",
    "level": "160",
    "subzone": "Las ramas del árbol Hakam",
    "zone": "Isla de Otomai",
    "step": 17,
    "type": "boss"
  },
  {
    "id": 345,
    "name": "Minotot",
    "image": "./assets/img/minotot.webp",
    "level": "160",
    "subzone": "Isla del Minotauroro",
    "zone": "Isla del Minotauroro",
    "step": 17,
    "type": "boss"
  },
  {
    "id": 346,
    "name": "Roble Blando",
    "image": "./assets/img/roble_blando.webp",
    "level": "140",
    "subzone": "Bosque Oscuro",
    "zone": "Bosque de los Abráknidos",
    "step": 17,
    "type": "boss"
  },
  {
    "id": 347,
    "name": "Sfinter Cell",
    "image": "./assets/img/bworker.webp",
    "level": "150",
    "subzone": "Castillo de Amakna",
    "zone": "Amakna",
    "step": 17,
    "type": "boss"
  },
  {
    "id": 348,
    "name": "Silf el Rasgabola Mayor",
    "image": "./assets/img/silf_el_rasgabola_mayor.webp",
    "level": "110",
    "subzone": "lanuras Herbosas",
    "zone": "Isla de Otomai",
    "step": 17,
    "type": "boss"
  },
  {
    "id": 349,
    "name": "Thor Pestruz",
    "image": "./assets/img/thor_pestruz.webp",
    "level": "150",
    "subzone": "Circo de Cania",
    "zone": "Llanuras de Cania",
    "step": 17,
    "type": "boss"
  },
  {
    "id": 350,
    "name": "Ugah",
    "image": "./assets/img/ugah.webp",
    "level": "180",
    "subzone": "Territorio de los Fongos",
    "zone": "Landas de Sidimote",
    "step": 17,
    "type": "boss"
  }   
]
